pypbd.cp38-win_amd64.pyd
pypbd-2.2.2.dist-info/LICENSE
pypbd-2.2.2.dist-info/METADATA
pypbd-2.2.2.dist-info/WHEEL
pypbd-2.2.2.dist-info/top_level.txt
pypbd-2.2.2.dist-info/RECORD
