Metadata-Version: 2.1
Name: pyPBD
Version: 2.2.2
Summary: PBD Project Python Bindings
Home-page: https://github.com/InteractiveComputerGraphics/PositionBasedDynamics
Author: Interactive Computer Graphics
Author-email: 
License: MIT
Keywords: simulation rigid-bodies rigid-body-dynamics position-based-dynamics deformable-solids
License-File: LICENSE
Requires-Dist: numpy
Requires-Dist: pygame
Requires-Dist: pyopengl
